{
  "PARTER I:2-16": "kupbilecik",
  "PARTER I:2-17": "kupbilecik",
  "PARTER I:2-18": "kupbilecik",
  "PARTER I:2-19": "kupbilecik",
  "PARTER I:2-20": "kupbilecik",
  "PARTER I:2-21": "kupbilecik",
  "PARTER I:2-30": "kupbilecik",
  "PARTER I:2-31": "kupbilecik",
  "PARTER I:2-32": "kupbilecik",
  "PARTER I:2-33": "kupbilecik",
  "PARTER I:2-34": "kupbilecik",
  "PARTER I:3-35": "kupbilecik",
  "PARTER I:3-36": "kupbilecik",
  "PARTER I:3-37": "kupbilecik",
  "PARTER I:3-38": "kupbilecik",
  "PARTER I:3-39": "kupbilecik",
  "PARTER I:3-49": "kupbilecik",
  "PARTER I:3-50": "kupbilecik",
  "PARTER I:3-51": "kupbilecik",
  "PARTER I:3-52": "kupbilecik",
  "PARTER I:3-53": "kupbilecik",
  "PARTER I:3-54": "kupbilecik",
  "PARTER I:3-55": "kupbilecik",
  "PARTER I:5-100": "kupbilecik",
  "PARTER I:5-101": "kupbilecik",
  "PARTER I:5-102": "kupbilecik",
  "PARTER I:5-103": "kupbilecik",
  "PARTER II:6-2": "kupbilecik",
  "PARTER II:6-3": "kupbilecik",
  "PARTER II:6-4": "kupbilecik",
  "PARTER II:6-27": "kupbilecik",
  "PARTER II:6-28": "kupbilecik",
  "PARTER II:7-1": "kupbilecik",
  "PARTER II:7-2": "kupbilecik",
  "PARTER II:7-3": "kupbilecik",
  "PARTER II:7-4": "kupbilecik",
  "PARTER II:7-5": "kupbilecik",
  "PARTER II:7-8": "kupbilecik",
  "PARTER II:7-9": "kupbilecik",
  "PARTER II:7-26": "kupbilecik",
  "PARTER II:7-27": "kupbilecik",
  "PARTER II:7-28": "kupbilecik",
  "PARTER II:7-29": "kupbilecik",
  "PARTER II:7-30": "kupbilecik",
  "PARTER II:9-1": "kupbilecik",
  "PARTER II:9-2": "kupbilecik",
  "PARTER II:9-3": "kupbilecik",
  "PARTER II:9-4": "kupbilecik",
  "PARTER II:9-5": "kupbilecik",
  "PARTER II:9-6": "kupbilecik",
  "PARTER II:9-7": "kupbilecik",
  "PARTER II:9-8": "kupbilecik",
  "PARTER II:9-9": "kupbilecik",
  "PARTER II:9-10": "kupbilecik",
  "PARTER II:10-1": "kupbilecik",
  "PARTER II:10-2": "kupbilecik",
  "PARTER II:10-3": "kupbilecik",
  "PARTER II:10-4": "kupbilecik",
  "PARTER II:10-5": "kupbilecik",
  "PARTER II:10-6": "kupbilecik",
  "PARTER II:10-7": "kupbilecik",
  "PARTER II:10-8": "kupbilecik",
  "PARTER II:10-9": "kupbilecik",
  "PARTER II:10-10": "kupbilecik",
  "PARTER II:13-1": "kupbilecik",
  "PARTER II:13-2": "kupbilecik",
  "PARTER II:13-3": "kupbilecik",
  "PARTER II:13-4": "kupbilecik",
  "PARTER II:13-5": "kupbilecik",
  "PARTER II:13-6": "kupbilecik",
  "PARTER II:13-7": "kupbilecik",
  "PARTER II:13-8": "kupbilecik",
  "PARTER II:13-9": "kupbilecik",
  "PARTER II:13-10": "kupbilecik",
  "PARTER II:13-11": "kupbilecik",
  "PARTER II:13-12": "kupbilecik",
  "PARTER II:13-13": "kupbilecik",
  "PARTER II:13-14": "kupbilecik",
  "PARTER II:13-15": "kupbilecik",
  "PARTER II:13-22": "kupbilecik",
  "PARTER II:13-23": "kupbilecik",
  "PARTER II:13-24": "kupbilecik",
  "PARTER II:13-25": "kupbilecik",
  "PARTER II:13-26": "kupbilecik",
  "PARTER II:13-27": "kupbilecik",
  "PARTER II:13-28": "kupbilecik",
  "PARTER II:13-29": "kupbilecik",
  "PARTER II:13-30": "kupbilecik",
  "PARTER II:13-31": "kupbilecik",
  "PARTER II:13-32": "kupbilecik",
  "PARTER II:13-33": "kupbilecik",
  "PARTER II:13-34": "kupbilecik",
  "PARTER II:14-1": "kupbilecik",
  "PARTER II:14-2": "kupbilecik",
  "PARTER II:14-3": "kupbilecik",
  "PARTER II:14-4": "kupbilecik",
  "PARTER II:14-5": "kupbilecik",
  "PARTER II:14-6": "kupbilecik",
  "PARTER II:14-7": "kupbilecik",
  "PARTER II:14-8": "kupbilecik",
  "PARTER II:14-9": "kupbilecik",
  "PARTER II:14-10": "kupbilecik",
  "PARTER II:14-11": "kupbilecik",
  "PARTER II:14-12": "kupbilecik",
  "PARTER II:14-13": "kupbilecik",
  "PARTER II:14-14": "kupbilecik",
  "PARTER II:14-17": "kupbilecik",
  "PARTER II:14-18": "kupbilecik",
  "PARTER II:14-21": "kupbilecik",
  "PARTER II:14-22": "kupbilecik",
  "PARTER II:14-23": "kupbilecik",
  "PARTER II:14-24": "kupbilecik",
  "PARTER II:14-25": "kupbilecik",
  "PARTER II:14-26": "kupbilecik",
  "PARTER II:14-27": "kupbilecik",
  "PARTER II:14-28": "kupbilecik",
  "PARTER II:14-29": "kupbilecik",
  "PARTER II:14-30": "kupbilecik",
  "PARTER II:14-31": "kupbilecik",
  "PARTER II:14-32": "kupbilecik",
  "BALKON I:2-31": "kupbilecik",
  "BALKON I:2-32": "kupbilecik",
  "BALKON I:2-33": "kupbilecik",
  "BALKON I:2-34": "kupbilecik",
  "BALKON I:2-35": "kupbilecik",
  "BALKON I:2-36": "kupbilecik",
  "BALKON I:2-37": "kupbilecik",
  "BALKON I:2-38": "kupbilecik",
  "BALKON I:2-39": "kupbilecik",
  "BALKON I:2-40": "kupbilecik",
  "BALKON I:2-41": "kupbilecik",
  "BALKON I:2-42": "kupbilecik",
  "BALKON I:2-43": "kupbilecik",
  "BALKON I:2-50": "kupbilecik",
  "BALKON I:2-51": "kupbilecik",
  "BALKON I:2-52": "kupbilecik",
  "BALKON I:2-53": "kupbilecik",
  "BALKON I:2-54": "kupbilecik",
  "BALKON I:2-55": "kupbilecik",
  "BALKON I:2-56": "kupbilecik",
  "BALKON I:2-57": "kupbilecik",
  "BALKON I:2-58": "kupbilecik",
  "BALKON I:2-59": "kupbilecik",
  "BALKON I:2-60": "kupbilecik",
  "Sektor 1:9-27": "biletyna",
  "Sektor 1:9-28": "biletyna",
  "Sektor 1:9-29": "biletyna",
  "Sektor 1:9-30": "biletyna",
  "Sektor 1:9-31": "biletyna",
  "Sektor 1:9-32": "biletyna",
  "Sektor 1:10-25": "biletyna",
  "Sektor 1:10-26": "biletyna",
  "Sektor 1:10-27": "biletyna",
  "Sektor 1:10-28": "biletyna",
  "Sektor 1:10-29": "biletyna",
  "Sektor 1:10-30": "biletyna",
  "Sektor 1:10-31": "biletyna",
  "Sektor 1:10-32": "biletyna",
  "Sektor 1:11-23": "biletyna",
  "Sektor 1:11-24": "biletyna",
  "Sektor 1:11-25": "biletyna",
  "Sektor 1:11-26": "biletyna",
  "Sektor 1:11-27": "biletyna",
  "Sektor 1:11-28": "biletyna",
  "Sektor 1:11-29": "biletyna",
  "Sektor 1:11-30": "biletyna",
  "Sektor 1:11-31": "biletyna",
  "Sektor 1:11-32": "biletyna",
  "Sektor 1:11-33": "biletyna",
  "Sektor 1:11-34": "biletyna",
  "Sektor 1:18-6": "biletyna",
  "Sektor 1:18-7": "biletyna",
  "Sektor 1:18-8": "biletyna",
  "Sektor 1:18-9": "biletyna",
  "Sektor 1:18-10": "biletyna",
  "Sektor 1:18-11": "biletyna",
  "Sektor 1:18-12": "biletyna",
  "BALKON I:3-61": "biletyna",
  "BALKON I:3-62": "biletyna",
  "BALKON I:3-63": "biletyna",
  "BALKON I:3-64": "biletyna",
  "BALKON I:3-65": "biletyna",
  "BALKON I:3-66": "biletyna",
  "BALKON I:3-67": "biletyna",
  "BALKON I:3-68": "biletyna",
  "BALKON I:3-69": "biletyna",
  "BALKON I:3-70": "biletyna",
  "BALKON I:3-71": "biletyna",
  "BALKON I:3-72": "biletyna",
  "BALKON I:3-73": "biletyna",
  "BALKON I:3-74": "biletyna",
  "BALKON I:3-79": "biletyna",
  "BALKON I:3-80": "biletyna",
  "BALKON I:3-81": "biletyna",
  "BALKON I:3-82": "biletyna",
  "BALKON I:3-83": "biletyna",
  "BALKON I:3-84": "biletyna",
  "BALKON I:3-85": "biletyna",
  "BALKON I:3-86": "biletyna",
  "BALKON I:3-87": "biletyna",
  "BALKON I:3-88": "biletyna",
  "BALKON I:3-89": "biletyna",
  "BALKON I:3-90": "biletyna",
  "BALKON I:3-91": "biletyna",
  "BALKON I:3-92": "biletyna",
  "BALKON I:1-30": "ebilet",
  "BALKON I:1-29": "ebilet",
  "BALKON I:1-28": "ebilet",
  "BALKON I:1-27": "ebilet",
  "BALKON I:1-26": "ebilet",
  "BALKON I:1-25": "ebilet",
  "BALKON I:1-24": "ebilet",
  "BALKON I:1-23": "ebilet",
  "BALKON I:1-22": "ebilet",
  "BALKON I:1-21": "ebilet",
  "BALKON I:1-20": "ebilet",
  "BALKON I:1-19": "ebilet",
  "BALKON I:1-9": "ebilet",
  "BALKON I:1-8": "ebilet",
  "BALKON I:1-7": "ebilet",
  "BALKON I:1-6": "ebilet",
  "BALKON I:1-5": "ebilet",
  "BALKON I:1-4": "ebilet",
  "BALKON I:1-3": "ebilet",
  "BALKON I:1-2": "ebilet",
  "BALKON I:1-1": "ebilet",
  "PARTER II:12-11": "ebilet",
  "PARTER II:12-10": "ebilet",
  "PARTER II:12-9": "ebilet",
  "PARTER II:12-8": "ebilet",
  "PARTER II:12-7": "ebilet",
  "PARTER II:12-6": "ebilet",
  "PARTER II:12-5": "ebilet",
  "PARTER II:12-4": "ebilet",
  "PARTER II:12-3": "ebilet",
  "PARTER II:12-2": "ebilet",
  "PARTER II:12-1": "ebilet",
  "PARTER II:11-8": "ebilet",
  "PARTER II:11-7": "ebilet",
  "PARTER II:11-6": "ebilet",
  "PARTER II:11-5": "ebilet",
  "PARTER II:11-4": "ebilet",
  "PARTER II:11-3": "ebilet",
  "PARTER II:11-2": "ebilet",
  "PARTER II:11-1": "ebilet",
  "PARTER II:8-30": "ebilet",
  "PARTER II:8-29": "ebilet",
  "PARTER II:8-28": "ebilet",
  "PARTER II:8-27": "ebilet",
  "PARTER II:8-26": "ebilet",
  "PARTER II:8-25": "ebilet",
  "PARTER II:8-24": "ebilet",
  "PARTER I:4-78": "ebilet",
  "PARTER I:4-77": "ebilet",
  "PARTER I:4-76": "ebilet",
  "PARTER I:4-75": "ebilet",
  "PARTER I:4-74": "ebilet",
  "PARTER I:4-73": "ebilet",
  "PARTER I:4-72": "ebilet",
  "PARTER I:4-71": "ebilet",
  "PARTER I:4-70": "ebilet",
  "PARTER I:4-69": "ebilet",
  "PARTER I:4-68": "ebilet",
  "PARTER I:4-65": "ebilet",
  "PARTER I:4-64": "ebilet",
  "PARTER I:4-63": "ebilet",
  "PARTER I:4-62": "ebilet",
  "PARTER I:4-61": "ebilet",
  "PARTER I:4-60": "ebilet",
  "PARTER I:4-59": "ebilet",
  "PARTER I:4-58": "ebilet",
  "PARTER I:4-57": "ebilet",
  "PARTER I:1-15": "ebilet",
  "PARTER I:1-14": "ebilet",
  "PARTER I:1-13": "ebilet",
  "PARTER I:1-2": "ebilet",
  "PARTER I:1-1": "ebilet"
}